<Properties StartupConfiguration="{1AFDB9DE-22AB-421D-AE5C-93D8B0B88B69}|Default">
  <MonoDevelop.Ide.ItemProperties.task1__lab2 PreferredExecutionTarget="MonoDevelop.Default" />
  <MonoDevelop.Ide.Workbench ActiveDocument="task1_lab2/Program.cs">
    <Files>
      <File FileName="task1_lab2/Program.cs" Line="32" Column="2" />
    </Files>
  </MonoDevelop.Ide.Workbench>
  <MonoDevelop.Ide.DebuggingService.PinnedWatches />
  <MonoDevelop.Ide.Workspace ActiveConfiguration="Debug|x86" />
  <MonoDevelop.Ide.DebuggingService.Breakpoints>
    <BreakpointStore />
  </MonoDevelop.Ide.DebuggingService.Breakpoints>
  <MultiItemStartupConfigurations />
</Properties>